./.gitignore
./PKG-INFO
./__init__.py
./pyproject.toml
./test.py
./video_hash_tmk.py
feluda_video_hash_tmk-0.1.0.dist-info/METADATA
feluda_video_hash_tmk-0.1.0.dist-info/WHEEL
feluda_video_hash_tmk-0.1.0.dist-info/RECORD
